edc_pharmacy/__init__.py
edc_pharmacy/action_items.py
edc_pharmacy/admin_mixin.py
edc_pharmacy/admin_site.py
edc_pharmacy/approve_prescription.py
edc_pharmacy/apps.py
edc_pharmacy/auth_objects.py
edc_pharmacy/auths.py
edc_pharmacy/choices.py
edc_pharmacy/constants.py
edc_pharmacy/dosage_calculator.py
edc_pharmacy/dosage_per_day.py
edc_pharmacy/exceptions.py
edc_pharmacy/list_data.py
edc_pharmacy/navbars.py
edc_pharmacy/offline_models.py
edc_pharmacy/settings.py
edc_pharmacy/urls.py
edc_pharmacy/admin/__init__.py
edc_pharmacy/admin/autocomplete_admin.py
edc_pharmacy/admin/list_filters.py
edc_pharmacy/admin/model_admin_mixin.py
edc_pharmacy/admin/remove_fields_for_blinded_users.py
edc_pharmacy/admin/scan_duplicates_admin.py
edc_pharmacy/admin/utils.py
edc_pharmacy/admin/actions/__init__.py
edc_pharmacy/admin/actions/allocate_stock_to_subject.py
edc_pharmacy/admin/actions/confirm_stock.py
edc_pharmacy/admin/actions/delete_items_for_stock_request.py
edc_pharmacy/admin/actions/delete_order_items.py
edc_pharmacy/admin/actions/delete_receive_items.py
edc_pharmacy/admin/actions/go_to_add_repack_request.py
edc_pharmacy/admin/actions/go_to_allocations.py
edc_pharmacy/admin/actions/go_to_stock.py
edc_pharmacy/admin/actions/prepare_stock_request_items.py
edc_pharmacy/admin/actions/print_labels.py
edc_pharmacy/admin/actions/print_stock_labels.py
edc_pharmacy/admin/actions/print_stock_report.py
edc_pharmacy/admin/actions/print_transfer_stock_manifest.py
edc_pharmacy/admin/actions/process_repack_request.py
edc_pharmacy/admin/actions/storage_bin.py
edc_pharmacy/admin/actions/transfer_stock.py
edc_pharmacy/admin/medication/__init__.py
edc_pharmacy/admin/medication/assignment_admin.py
edc_pharmacy/admin/medication/dosage_guideline_admin.py
edc_pharmacy/admin/medication/formulation_admin.py
edc_pharmacy/admin/medication/formulation_type_admin.py
edc_pharmacy/admin/medication/frequency_units_admin.py
edc_pharmacy/admin/medication/medication_admin.py
edc_pharmacy-1.2.3.dist-info/licenses/AUTHORS
edc_pharmacy-1.2.3.dist-info/licenses/LICENSE
edc_pharmacy-1.2.3.dist-info/METADATA
edc_pharmacy-1.2.3.dist-info/WHEEL
edc_pharmacy-1.2.3.dist-info/top_level.txt
edc_pharmacy-1.2.3.dist-info/RECORD
