Metadata-Version: 2.4
Name: edc-pharmacy
Version: 1.2.3
Summary: Pharmacy models and classes for clinicedc/edc projects
Home-page: https://github.com/clinicedc/edc-pharmacy
Author: Erik van Widenfelt
Author-email: ew2789@gmail.com
License: GPL license, see LICENSE
Keywords: django Edc pharmacy,clinicedc,clinical trials
Classifier: Environment :: Web Environment
Classifier: Framework :: Django
Classifier: Framework :: Django :: 5.2
Classifier: Intended Audience :: Developers
Classifier: Intended Audience :: Science/Research
Classifier: Operating System :: OS Independent
Classifier: Programming Language :: Python :: 3.12
Classifier: License :: OSI Approved :: GNU General Public License v3 (GPLv3)
Requires-Python: >=3.12
License-File: LICENSE
License-File: AUTHORS
Requires-Dist: reportlab
Requires-Dist: django-sequences
Requires-Dist: celery
Requires-Dist: redis
Requires-Dist: edc-pylabels
Dynamic: license-file
